formula/__init__.py
formula/sdk.py
formula/hooks/__init__.py
formula/hooks/hook.py
formula/models/__init__.py
formula/models/base.py
formula/models/utils/cast_models.py
formula/models/utils/json_map.py
formula/net/__init__.py
formula/net/environment/__init__.py
formula/net/environment/environment.py
formula/net/headers/__init__.py
formula/net/headers/base_header.py
formula/net/request_chain/__init__.py
formula/net/request_chain/request_chain.py
formula/net/request_chain/handlers/__init__.py
formula/net/request_chain/handlers/base_handler.py
formula/net/request_chain/handlers/hook_handler.py
formula/net/request_chain/handlers/http_handler.py
formula/net/request_chain/handlers/retry_handler.py
formula/net/transport/__init__.py
formula/net/transport/request.py
formula/net/transport/request_error.py
formula/net/transport/response.py
formula/net/transport/serializer.py
formula/net/transport/utils.py
formula/services/__init__.py
formula/services/circuits.py
formula/services/constructors.py
formula/services/drivers.py
formula/services/finishing_status.py
formula/services/lap_times.py
formula/services/pit_stops.py
formula/services/qualifying.py
formula/services/results.py
formula/services/schedules.py
formula/services/seasons.py
formula/services/standings.py
formula/services/utils/base_service.py
formula/services/utils/default_headers.py
formula/services/utils/validator.py
formula_client-1.0.0.dist-info/LICENSE
formula_client-1.0.0.dist-info/METADATA
formula_client-1.0.0.dist-info/WHEEL
formula_client-1.0.0.dist-info/top_level.txt
formula_client-1.0.0.dist-info/RECORD
